corganizeclient/__init__.py
corganizeclient/client.py
corganizeclient-0.0.17.dist-info/LICENSE
corganizeclient-0.0.17.dist-info/METADATA
corganizeclient-0.0.17.dist-info/WHEEL
corganizeclient-0.0.17.dist-info/top_level.txt
corganizeclient-0.0.17.dist-info/RECORD
