Metadata-Version: 2.1
Name: corganizeclient
Version: 0.0.17
Summary: A Python client to interact with corganize server
Home-page: UNKNOWN
Author: Jaeseo Park
License: UNKNOWN
Platform: UNKNOWN
Classifier: Programming Language :: Python :: 3
Classifier: Operating System :: OS Independent
Requires-Python: >=3.6
License-File: LICENSE
Requires-Dist: requests
